{"cameraMode":{"drawMode":0,"name":"Shaded","section":"Shading Mode"},"sceneLighting":false,"audioPlay":false,"sceneViewState":{"showFog":true,"showMaterialUpdate":false,"showSkybox":false,"showFlares":true,"showImageEffects":true,"showParticleSystems":true},"in2DMode":false,"pivot":{"x":1.4368653297424317,"y":3.6250686645507814,"z":0.7266868352890015},"rotation":{"x":-0.2681773900985718,"y":-0.5646759867668152,"z":0.20093944668769837,"w":-0.7542845010757446},"size":6.857366561889648,"orthographic":false}